linearRegression_moamed/__init__.py
linearRegression_moamed/linearRegression_moamed.py
linearRegression_moamed-0.1.0.dist-info/LICENSE.txt
linearRegression_moamed-0.1.0.dist-info/METADATA
linearRegression_moamed-0.1.0.dist-info/WHEEL
linearRegression_moamed-0.1.0.dist-info/top_level.txt
linearRegression_moamed-0.1.0.dist-info/RECORD
